MANIFEST.in
README.md
VERSION
requirements.txt
setup.cfg
setup.py
rhasspy_wake_snowboy_hermes.egg-info/PKG-INFO
rhasspy_wake_snowboy_hermes.egg-info/SOURCES.txt
rhasspy_wake_snowboy_hermes.egg-info/dependency_links.txt
rhasspy_wake_snowboy_hermes.egg-info/entry_points.txt
rhasspy_wake_snowboy_hermes.egg-info/requires.txt
rhasspy_wake_snowboy_hermes.egg-info/top_level.txt
rhasspywake_snowboy_hermes/__init__.py
rhasspywake_snowboy_hermes/__main__.py
rhasspywake_snowboy_hermes/py.typed
rhasspywake_snowboy_hermes/models/hey_extreme.umdl
rhasspywake_snowboy_hermes/models/jarvis.umdl
rhasspywake_snowboy_hermes/models/neoya.umdl
rhasspywake_snowboy_hermes/models/smart_mirror.umdl
rhasspywake_snowboy_hermes/models/snowboy.umdl
rhasspywake_snowboy_hermes/models/subex.umdl
rhasspywake_snowboy_hermes/models/view_glass.umdl